MANIFEST.in
README.md
VERSION.txt
requirements.txt
setup.py
balloon_block_editor/__init__.py
balloon_block_editor/fields.py
balloon_block_editor/models.py
balloon_block_editor/urls.py
balloon_block_editor/views.py
balloon_block_editor/migrations/0001_initial.py
balloon_block_editor/migrations/__init__.py
balloon_block_editor/static/balloon_block_editor/ckeditor.js
balloon_block_editor/templates/balloon_block_editor/widget.html
core/__init__.py
core/admin.py
core/asgi.py
core/models.py
core/settings.py
core/urls.py
core/wsgi.py
core/migrations/0001_initial.py
core/migrations/0002_auto_20200911_0510.py
core/migrations/0003_auto_20200911_0513.py
core/migrations/__init__.py
django_balloon_block_editor.egg-info/PKG-INFO
django_balloon_block_editor.egg-info/SOURCES.txt
django_balloon_block_editor.egg-info/dependency_links.txt
django_balloon_block_editor.egg-info/not-zip-safe
django_balloon_block_editor.egg-info/requires.txt
django_balloon_block_editor.egg-info/top_level.txt