Metadata-Version: 1.0
Name: django-balloon-block-editor
Version: 1.0.0
Summary: Implementation of CKEditor's Balloon Block Editor, for Django.
Home-page: https://github.com/matix-io/django-balloon-block-editor
Author: Connor Bode
Author-email: connor@matix.io
License: MIT
Platform: UNKNOWN
